Metadata-Version: 2.1
Name: tkitTextClassification
Version: 0.0.0.2
Summary: Terry toolkit
Home-page: https://www.terrychan.org/transformers-SentenceSimilarity/
Author: Terry Chan
Author-email: napoler2008@gmail.com
License: UNKNOWN
Platform: UNKNOWN
